spiderfoot_mcp/__init__.py
spiderfoot_mcp/server.py
spiderfoot_mcp-1.0.0.dist-info/licenses/LICENSE
spiderfoot_mcp-1.0.0.dist-info/METADATA
spiderfoot_mcp-1.0.0.dist-info/WHEEL
spiderfoot_mcp-1.0.0.dist-info/entry_points.txt
spiderfoot_mcp-1.0.0.dist-info/top_level.txt
spiderfoot_mcp-1.0.0.dist-info/RECORD
