Metadata-Version: 2.4
Name: spiderfoot-mcp
Version: 1.0.0
Summary: Model Context Protocol server for SpiderFoot OSINT automation
Author-email: Vlatko Kosturjak <vlatko.kosturjak@marlink.com>
License: MIT
Project-URL: Homepage, https://github.com/marlinkcyber/spiderfoot-mcp
Project-URL: Repository, https://github.com/marlinkcyber/spiderfoot-mcp
Project-URL: Documentation, https://github.com/marlinkcyber/spiderfoot-mcp
Project-URL: Bug Tracker, https://github.com/marlinkcyber/spiderfoot-mcp/issues
Keywords: spiderfoot,osint,security,mcp,model-context-protocol,reconnaissance
Classifier: Development Status :: 4 - Beta
Classifier: Intended Audience :: Developers
Classifier: Intended Audience :: Information Technology
Classifier: License :: OSI Approved :: MIT License
Classifier: Programming Language :: Python :: 3
Classifier: Programming Language :: Python :: 3.8
Classifier: Programming Language :: Python :: 3.9
Classifier: Programming Language :: Python :: 3.10
Classifier: Programming Language :: Python :: 3.11
Classifier: Programming Language :: Python :: 3.12
Classifier: Topic :: Security
Classifier: Topic :: Software Development :: Libraries :: Python Modules
Classifier: Topic :: Communications
Requires-Python: >=3.8
License-File: LICENSE
Requires-Dist: spiderfoot-client>=1.0.0
Requires-Dist: fastmcp>=2.10.0
Requires-Dist: python-dotenv>=1.0.0
Provides-Extra: dev
Requires-Dist: pytest>=7.0.0; extra == "dev"
Requires-Dist: pytest-cov>=4.0.0; extra == "dev"
Requires-Dist: pytest-asyncio>=0.21.0; extra == "dev"
Requires-Dist: black>=23.0.0; extra == "dev"
Requires-Dist: flake8>=6.0.0; extra == "dev"
Requires-Dist: mypy>=1.0.0; extra == "dev"
Requires-Dist: types-requests; extra == "dev"
Dynamic: license-file
